django_adx/__init__.py
django_adx/utils.py
django_adx/builders/__init__.py
django_adx/builders/adx.py
django_adx/models/__init__.py
django_adx/models/adx/__init__.py
django_adx/models/adx/data.py
django_adx/models/adx/definition.py
django_adx/models/adx/time_period.py
django_adx/models/dhis2/__init__.py
django_adx/models/dhis2/dataset.py
django_adx/models/dhis2/enum.py
django_adx/models/dhis2/metadata.py
django_adx/models/dhis2/program.py
django_adx/models/dhis2/type.py
django_adx/serializers/__init__.py
django_adx/serializers/adx.py
django_adx/services/__init__.py
django_adx/services/adx_metadata.py
django_adx/services/utils.py
django_adx-1.0.3.dist-info/LICENSE
django_adx-1.0.3.dist-info/LICENSE.md
django_adx-1.0.3.dist-info/METADATA
django_adx-1.0.3.dist-info/WHEEL
django_adx-1.0.3.dist-info/top_level.txt
django_adx-1.0.3.dist-info/RECORD
